{
  "chapter_name_arabic": "البقرة",
  "chapter_name_transcribed": "Al-Baqarah",
  "chapter_name_translated": {
    "bg": {
      "language_name": "english",
      "name": "The Cow"
    },
    "bs": {
      "language_name": "bosnian",
      "name": "Krava"
    },
    "ce": {
      "language_name": "english",
      "name": "The Cow"
    },
    "cs": {
      "language_name": "english",
      "name": "The Cow"
    },
    "de": {
      "language_name": "english",
      "name": "The Cow"
    },
    "en": {
      "language_name": "english",
      "name": "The Cow"
    },
    "es": {
      "language_name": "spanish",
      "name": "La Vaca"
    },
    "fi": {
      "language_name": "english",
      "name": "The Cow"
    },
    "fr": {
      "language_name": "french",
      "name": "La vache"
    },
    "he": {
      "language_name": "english",
      "name": "The Cow"
    },
    "id": {
      "language_name": "indonesian",
      "name": "Sapi Betina"
    },
    "it": {
      "language_name": "italian",
      "name": "La Giovenca"
    },
    "nl": {
      "language_name": "dutch",
      "name": "De Koe"
    },
    "no": {
      "language_name": "english",
      "name": "The Cow"
    },
    "pl": {
      "language_name": "english",
      "name": "The Cow"
    },
    "pt": {
      "language_name": "english",
      "name": "The Cow"
    },
    "ro": {
      "language_name": "english",
      "name": "The Cow"
    },
    "ru": {
      "language_name": "russian",
      "name": "Корова"
    },
    "sq": {
      "language_name": "english",
      "name": "The Cow"
    },
    "sr": {
      "language_name": "english",
      "name": "The Cow"
    },
    "sv": {
      "language_name": "swedish",
      "name": "Kon"
    },
    "tr": {
      "language_name": "turkish",
      "name": "Bakara"
    },
    "tt": {
      "language_name": "english",
      "name": "The Cow"
    },
    "ug": {
      "language_name": "english",
      "name": "The Cow"
    },
    "uk": {
      "language_name": "english",
      "name": "The Cow"
    },
    "zh": {
      "language_name": "chinese",
      "name": "黄牛"
    }
  },
  "chapter_name_transliterated": "Al-Baqarah",
  "chapter_number": 2,
  "number_of_ayahs": 286,
  "pages": [
    2,
    49
  ],
  "revelation_order": 87,
  "revelation_place": "madinah",
  "verses": [
    {
      "hizb_number": 1,
      "id": 7,
      "juz_number": 1,
      "manzil_number": 1,
      "page_number": 4,
      "rub_el_hizb_number": 1,
      "ruku_number": 3,
      "sajdah_number": null,
      "text_uthmani": "يَكَادُ ٱلْبَرْقُ يَخْطَفُ أَبْصَـٰرَهُمْ ۖ كُلَّمَآ أَضَآءَ لَهُم مَّشَوْا۟ فِيهِ وَإِذَآ أَظْلَمَ عَلَيْهِمْ قَامُوا۟ ۚ وَلَوْ شَآءَ ٱللَّهُ لَذَهَبَ بِسَمْعِهِمْ وَأَبْصَـٰرِهِمْ ۚ إِنَّ ٱللَّهَ عَلَىٰ كُلِّ شَىْءٍ قَدِيرٌ",
      "text_uthmani_tajweed": "يَكَادُ [h:75[ٱ]لْبَرْقُ يَخْطَفُ أَ[q:76[بْ]صَ[n[ـٰ]رَهُمْ‌ۖ كُلَّم[o[َآ] أَض[o[َا]ٓءَ لَه[w:77[ُم م]َّشَوْ[s[اْ] فِيهِ وَإِذ[o[َآ] أَظْلَمَ عَلَيْهِمْ قَامُو[s[اْ‌ۚ] وَلَوْ ش[o[َا]ٓءَ [h:78[ٱ]للَّهُ لَذَهَبَ بِسَمْعِهِمْ وَأَ[q:79[بْ]صَ[n[ـٰ]رِهِمْ‌ۚ إِ[g[نّ]َ [h:80[ٱ]للَّهَ عَلَىٰ كُلِّ ش[f:81[َىْءٍ ق]َد[p[ِي]رٌ",
      "text_uthmani_tajweed_parsed": "يَكَادُ <tajweed class='ham_wasl' data-type='hamza-wasl' data-description='Hamzat ul Wasl' data-tajweed=':75'>ٱ</tajweed>لْبَرْقُ يَخْطَفُ أَ<tajweed class='qlq' data-type='qalaqah' data-description='Qalaqah' data-tajweed=':76'>بْ</tajweed>صَ<tajweed class='madda_normal' data-type='madda-normal' data-description='Normal Prolongation: 2 Vowels'>ـٰ</tajweed>رَهُمْ‌ۖ كُلَّم<tajweed class='madda_obligatory' data-type='madda-obligatory' data-description='Obligatory Prolongation: 4-5 Vowels'>َآ</tajweed> أَض<tajweed class='madda_obligatory' data-type='madda-obligatory' data-description='Obligatory Prolongation: 4-5 Vowels'>َا</tajweed>ٓءَ لَه<tajweed class='idghm_shfw' data-type='idgham-shafawi' data-description='Idgham Shafawi - With Meem' data-tajweed=':77'>ُم م</tajweed>َّشَوْ<tajweed class='slnt' data-type='silent' data-description='Silent'>اْ</tajweed> فِيهِ وَإِذ<tajweed class='madda_obligatory' data-type='madda-obligatory' data-description='Obligatory Prolongation: 4-5 Vowels'>َآ</tajweed> أَظْلَمَ عَلَيْهِمْ قَامُو<tajweed class='slnt' data-type='silent' data-description='Silent'>اْ‌ۚ</tajweed> وَلَوْ ش<tajweed class='madda_obligatory' data-type='madda-obligatory' data-description='Obligatory Prolongation: 4-5 Vowels'>َا</tajweed>ٓءَ <tajweed class='ham_wasl' data-type='hamza-wasl' data-description='Hamzat ul Wasl' data-tajweed=':78'>ٱ</tajweed>للَّهُ لَذَهَبَ بِسَمْعِهِمْ وَأَ<tajweed class='qlq' data-type='qalaqah' data-description='Qalaqah' data-tajweed=':79'>بْ</tajweed>صَ<tajweed class='madda_normal' data-type='madda-normal' data-description='Normal Prolongation: 2 Vowels'>ـٰ</tajweed>رِهِمْ‌ۚ إِ<tajweed class='ghn' data-type='ghunnah' data-description='Ghunnah: 2 Vowels'>نّ</tajweed>َ <tajweed class='ham_wasl' data-type='hamza-wasl' data-description='Hamzat ul Wasl' data-tajweed=':80'>ٱ</tajweed>للَّهَ عَلَىٰ كُلِّ ش<tajweed class='ikhf' data-type='ikhafa' data-description='Ikhafa'' data-tajweed=':81'>َىْءٍ ق</tajweed>َد<tajweed class='madda_permissible' data-type='madda-permissible' data-description='Permissible Prolongation: 2, 4, 6 Vowels'>ِي</tajweed>رٌ",
      "text_uthmani_transcribed": "Yakādul-barqu yakhṭafu abṣārahum, kullamā aḍā'a lahum masyau fīh(i), wa iżā aẓlama 'alaihim qāmū, wa lau syā'allāhu lażahaba bisam'ihim wa abṣārihim, innallāha 'alā kulli syai'in qadīr(un).",
      "translations": [
        {
          "id": 91384,
          "resource_id": 19,
          "text": "The lightning almost snatcheth away their sight from them. As often as it flasheth forth for them they walk therein, and when it darkeneth against them they stand still. If Allah willed, He could destroy their hearing and their sight. Lo! Allah is able to do all things."
        },
        {
          "id": 364314,
          "resource_id": 79,
          "text": "Готова молния отнять их зрения [они чуть не слепнут от ее яркого блеска]; как только она [молния] осветит для них, они идут [продвигаются] при ней [при свете молнии]. А когда окажется над ними мрак [темнота], они стоят (на своих местах). И если бы пожелал Аллах, то унес бы [лишил бы] их слух и зрение: ведь Аллах над всякой вещью мощен [Он может все]!"
        },
        {
          "id": 257584,
          "resource_id": 45,
          "text": "Молния готова отнять у них зрение. Когда она вспыхивает, они отправляются в путь, когда же опускается мрак, они останавливаются. Если бы Аллах пожелал, Он лишил бы их слуха и зрения. Воистину, Аллах способен на всякую вещь."
        },
        {
          "id": 140562,
          "resource_id": 27,
          "text": "Der Blitz reißt ihnen beinahe das Augenlicht fort. Jedesmal, wenn er ihnen Helligkeit verbreitet, gehen sie darin. Und wenn es finster um sie wird, bleiben sie stehen. Wenn Allah wollte, nähme Er ihnen wahrlich Gehör und Augenlicht. Allah hat zu allem die Macht."
        }
      ],
      "verse_key": "2:1",
      "verse_number": 1,
      "words": [
        {
          "audio_url": "wbw/002_020_001.mp3",
          "char_type_name": "word",
          "code_v1": "ﭿ",
          "id": 23077,
          "line_number": 5,
          "page_number": 4,
          "position": 1,
          "text": "ﭿ",
          "text_uthmani": "يَكَادُ",
          "translation": {
            "language_name": "english",
            "text": "Almost"
          },
          "transliteration": {
            "language_name": "english",
            "text": "yakādu"
          }
        },
        {
          "audio_url": "wbw/002_020_002.mp3",
          "char_type_name": "word",
          "code_v1": "ﮀ",
          "id": 23078,
          "line_number": 5,
          "page_number": 4,
          "position": 2,
          "text": "ﮀ",
          "text_uthmani": "ٱلْبَرْقُ",
          "translation": {
            "language_name": "english",
            "text": "the lightning"
          },
          "transliteration": {
            "language_name": "english",
            "text": "l-barqu"
          }
        },
        {
          "audio_url": "wbw/002_020_003.mp3",
          "char_type_name": "word",
          "code_v1": "ﮁ",
          "id": 23079,
          "line_number": 5,
          "page_number": 4,
          "position": 3,
          "text": "ﮁ",
          "text_uthmani": "يَخْطَفُ",
          "translation": {
            "language_name": "english",
            "text": "snatches away"
          },
          "transliteration": {
            "language_name": "english",
            "text": "yakhṭafu"
          }
        },
        {
          "audio_url": "wbw/002_020_004.mp3",
          "char_type_name": "word",
          "code_v1": "ﮂﮃ",
          "id": 23080,
          "line_number": 6,
          "page_number": 4,
          "position": 4,
          "text": "ﮂﮃ",
          "text_uthmani": "أَبْصَـٰرَهُمْ ۖ",
          "translation": {
            "language_name": "english",
            "text": "their sight"
          },
          "transliteration": {
            "language_name": "english",
            "text": "abṣārahum"
          }
        },
        {
          "audio_url": "wbw/002_020_006.mp3",
          "char_type_name": "word",
          "code_v1": "ﮄ",
          "id": 23082,
          "line_number": 6,
          "page_number": 4,
          "position": 5,
          "text": "ﮄ",
          "text_uthmani": "كُلَّمَآ",
          "translation": {
            "language_name": "english",
            "text": "Whenever"
          },
          "transliteration": {
            "language_name": "english",
            "text": "kullamā"
          }
        },
        {
          "audio_url": "wbw/002_020_007.mp3",
          "char_type_name": "word",
          "code_v1": "ﮅ",
          "id": 23083,
          "line_number": 6,
          "page_number": 4,
          "position": 6,
          "text": "ﮅ",
          "text_uthmani": "أَضَآءَ",
          "translation": {
            "language_name": "english",
            "text": "it flashes"
          },
          "transliteration": {
            "language_name": "english",
            "text": "aḍāa"
          }
        },
        {
          "audio_url": "wbw/002_020_008.mp3",
          "char_type_name": "word",
          "code_v1": "ﮆ",
          "id": 23084,
          "line_number": 6,
          "page_number": 4,
          "position": 7,
          "text": "ﮆ",
          "text_uthmani": "لَهُم",
          "translation": {
            "language_name": "english",
            "text": "for them"
          },
          "transliteration": {
            "language_name": "english",
            "text": "lahum"
          }
        },
        {
          "audio_url": "wbw/002_020_009.mp3",
          "char_type_name": "word",
          "code_v1": "ﮇ",
          "id": 23085,
          "line_number": 6,
          "page_number": 4,
          "position": 8,
          "text": "ﮇ",
          "text_uthmani": "مَّشَوْا۟",
          "translation": {
            "language_name": "english",
            "text": "they walk"
          },
          "transliteration": {
            "language_name": "english",
            "text": "mashaw"
          }
        },
        {
          "audio_url": "wbw/002_020_010.mp3",
          "char_type_name": "word",
          "code_v1": "ﮈ",
          "id": 23086,
          "line_number": 6,
          "page_number": 4,
          "position": 9,
          "text": "ﮈ",
          "text_uthmani": "فِيهِ",
          "translation": {
            "language_name": "english",
            "text": "in it"
          },
          "transliteration": {
            "language_name": "english",
            "text": "fīhi"
          }
        },
        {
          "audio_url": "wbw/002_020_011.mp3",
          "char_type_name": "word",
          "code_v1": "ﮉ",
          "id": 23087,
          "line_number": 6,
          "page_number": 4,
          "position": 10,
          "text": "ﮉ",
          "text_uthmani": "وَإِذَآ",
          "translation": {
            "language_name": "english",
            "text": "and when"
          },
          "transliteration": {
            "language_name": "english",
            "text": "wa-idhā"
          }
        },
        {
          "audio_url": "wbw/002_020_012.mp3",
          "char_type_name": "word",
          "code_v1": "ﮊ",
          "id": 23088,
          "line_number": 6,
          "page_number": 4,
          "position": 11,
          "text": "ﮊ",
          "text_uthmani": "أَظْلَمَ",
          "translation": {
            "language_name": "english",
            "text": "it darkens"
          },
          "transliteration": {
            "language_name": "english",
            "text": "aẓlama"
          }
        },
        {
          "audio_url": "wbw/002_020_013.mp3",
          "char_type_name": "word",
          "code_v1": "ﮋ",
          "id": 23089,
          "line_number": 6,
          "page_number": 4,
          "position": 12,
          "text": "ﮋ",
          "text_uthmani": "عَلَيْهِمْ",
          "translation": {
            "language_name": "english",
            "text": "on them"
          },
          "transliteration": {
            "language_name": "english",
            "text": "ʿalayhim"
          }
        },
        {
          "audio_url": "wbw/002_020_014.mp3",
          "char_type_name": "word",
          "code_v1": "ﮌﮍ",
          "id": 23090,
          "line_number": 6,
          "page_number": 4,
          "position": 13,
          "text": "ﮌﮍ",
          "text_uthmani": "قَامُوا۟ ۚ",
          "translation": {
            "language_name": "english",
            "text": "they stand (still)"
          },
          "transliteration": {
            "language_name": "english",
            "text": "qāmū"
          }
        },
        {
          "audio_url": "wbw/002_020_016.mp3",
          "char_type_name": "word",
          "code_v1": "ﮎ",
          "id": 23092,
          "line_number": 7,
          "page_number": 4,
          "position": 14,
          "text": "ﮎ",
          "text_uthmani": "وَلَوْ",
          "translation": {
            "language_name": "english",
            "text": "And if"
          },
          "transliteration": {
            "language_name": "english",
            "text": "walaw"
          }
        },
        {
          "audio_url": "wbw/002_020_017.mp3",
          "char_type_name": "word",
          "code_v1": "ﮏ",
          "id": 23093,
          "line_number": 7,
          "page_number": 4,
          "position": 15,
          "text": "ﮏ",
          "text_uthmani": "شَآءَ",
          "translation": {
            "language_name": "english",
            "text": "had willed"
          },
          "transliteration": {
            "language_name": "english",
            "text": "shāa"
          }
        },
        {
          "audio_url": "wbw/002_020_018.mp3",
          "char_type_name": "word",
          "code_v1": "ﮐ",
          "id": 23094,
          "line_number": 7,
          "page_number": 4,
          "position": 16,
          "text": "ﮐ",
          "text_uthmani": "ٱللَّهُ",
          "translation": {
            "language_name": "english",
            "text": "Allah"
          },
          "transliteration": {
            "language_name": "english",
            "text": "l-lahu"
          }
        },
        {
          "audio_url": "wbw/002_020_019.mp3",
          "char_type_name": "word",
          "code_v1": "ﮑ",
          "id": 23095,
          "line_number": 7,
          "page_number": 4,
          "position": 17,
          "text": "ﮑ",
          "text_uthmani": "لَذَهَبَ",
          "translation": {
            "language_name": "english",
            "text": "He would certainly have taken away"
          },
          "transliteration": {
            "language_name": "english",
            "text": "ladhahaba"
          }
        },
        {
          "audio_url": "wbw/002_020_020.mp3",
          "char_type_name": "word",
          "code_v1": "ﮒ",
          "id": 23096,
          "line_number": 7,
          "page_number": 4,
          "position": 18,
          "text": "ﮒ",
          "text_uthmani": "بِسَمْعِهِمْ",
          "translation": {
            "language_name": "english",
            "text": "their hearing"
          },
          "transliteration": {
            "language_name": "english",
            "text": "bisamʿihim"
          }
        },
        {
          "audio_url": "wbw/002_020_021.mp3",
          "char_type_name": "word",
          "code_v1": "ﮓﮔ",
          "id": 23097,
          "line_number": 7,
          "page_number": 4,
          "position": 19,
          "text": "ﮓﮔ",
          "text_uthmani": "وَأَبْصَـٰرِهِمْ ۚ",
          "translation": {
            "language_name": "english",
            "text": "and their sight"
          },
          "transliteration": {
            "language_name": "english",
            "text": "wa-abṣārihim"
          }
        },
        {
          "audio_url": "wbw/002_020_023.mp3",
          "char_type_name": "word",
          "code_v1": "ﮕ",
          "id": 23099,
          "line_number": 7,
          "page_number": 4,
          "position": 20,
          "text": "ﮕ",
          "text_uthmani": "إِنَّ",
          "translation": {
            "language_name": "english",
            "text": "Indeed"
          },
          "transliteration": {
            "language_name": "english",
            "text": "inna"
          }
        },
        {
          "audio_url": "wbw/002_020_024.mp3",
          "char_type_name": "word",
          "code_v1": "ﮖ",
          "id": 23100,
          "line_number": 7,
          "page_number": 4,
          "position": 21,
          "text": "ﮖ",
          "text_uthmani": "ٱللَّهَ",
          "translation": {
            "language_name": "english",
            "text": "Allah"
          },
          "transliteration": {
            "language_name": "english",
            "text": "l-laha"
          }
        },
        {
          "audio_url": "wbw/002_020_025.mp3",
          "char_type_name": "word",
          "code_v1": "ﮗ",
          "id": 23101,
          "line_number": 7,
          "page_number": 4,
          "position": 22,
          "text": "ﮗ",
          "text_uthmani": "عَلَىٰ",
          "translation": {
            "language_name": "english",
            "text": "(is) on"
          },
          "transliteration": {
            "language_name": "english",
            "text": "ʿalā"
          }
        },
        {
          "audio_url": "wbw/002_020_026.mp3",
          "char_type_name": "word",
          "code_v1": "ﮘ",
          "id": 23102,
          "line_number": 7,
          "page_number": 4,
          "position": 23,
          "text": "ﮘ",
          "text_uthmani": "كُلِّ",
          "translation": {
            "language_name": "english",
            "text": "every"
          },
          "transliteration": {
            "language_name": "english",
            "text": "kulli"
          }
        },
        {
          "audio_url": "wbw/002_020_027.mp3",
          "char_type_name": "word",
          "code_v1": "ﮙ",
          "id": 23103,
          "line_number": 8,
          "page_number": 4,
          "position": 24,
          "text": "ﮙ",
          "text_uthmani": "شَىْءٍۢ",
          "translation": {
            "language_name": "english",
            "text": "thing"
          },
          "transliteration": {
            "language_name": "english",
            "text": "shayin"
          }
        },
        {
          "audio_url": "wbw/002_020_028.mp3",
          "char_type_name": "word",
          "code_v1": "ﮚ",
          "id": 23104,
          "line_number": 8,
          "page_number": 4,
          "position": 25,
          "text": "ﮚ",
          "text_uthmani": "قَدِيرٌۭ",
          "translation": {
            "language_name": "english",
            "text": "All-Powerful"
          },
          "transliteration": {
            "language_name": "english",
            "text": "qadīrun"
          }
        },
        {
          "audio_url": null,
          "char_type_name": "end",
          "code_v1": "ﮛ",
          "id": 23105,
          "line_number": 8,
          "page_number": 4,
          "position": 26,
          "text": "ﮛ",
          "text_uthmani": "٢٠",
          "translation": {
            "language_name": "english",
            "text": "(20)"
          },
          "transliteration": {
            "language_name": "english",
            "text": null
          }
        }
      ]
    }
  ]
}